esa/__about__.py
esa/__init__.py
esa/_performance.py
esa/_performance_jit.py
esa/performance310.pyd
esa/performance37.pyd
esa/performance38.pyd
esa/performance39.pyd
esa/saw.py
tests/__init__.py
tests/constants.py
tests/run_tests_for_all_python_versions.py
tests/test_saw.py
tests/test_snippets.py
esa-1.3.5.dist-info/LICENSE
esa-1.3.5.dist-info/METADATA
esa-1.3.5.dist-info/WHEEL
esa-1.3.5.dist-info/top_level.txt
esa-1.3.5.dist-info/RECORD
