Metadata-Version: 2.1
Name: esa
Version: 1.3.5
Summary: Easy SimAuto (ESA): An easy-to-use Python connector to PowerWorld Simulator Automation Server (SimAuto).
Home-page: https://github.com/mzy2240/ESA
Author: Zeyu Mao, Brandon Thayer, Yijing Liu
Author-email: zeyumao2@tamu.edu, blthayer@tamu.edu, yiji21@tamu.edu
License: Apache License 2.0
Keywords: Python,PowerWorld,PowerWorld Simulator,Simulator,PowerWorld Simulation Automation Server,SimAuto,Automation,Power Systems,Electric Power,Power,Easy SimAuto,ESA,Smart Grid,Numpy,Pandas
Classifier: Programming Language :: Python :: 3 :: Only
Classifier: Programming Language :: Python :: 3.7
Classifier: Programming Language :: Python :: 3.8
Classifier: Programming Language :: Python :: 3.9
Classifier: Programming Language :: Python :: 3.10
Classifier: License :: OSI Approved :: Apache Software License
Classifier: Operating System :: Microsoft :: Windows
Classifier: Development Status :: 5 - Production/Stable
Classifier: Environment :: Win32 (MS Windows)
Classifier: Intended Audience :: Developers
Classifier: Intended Audience :: Education
Classifier: Intended Audience :: Science/Research
Classifier: Natural Language :: English
Classifier: Topic :: Education
Classifier: Topic :: Scientific/Engineering
Classifier: Topic :: Software Development
Requires-Python: >=3.7
License-File: LICENSE
Requires-Dist: pandas (>=0.25)
Requires-Dist: numpy (>=1.19.5)
Requires-Dist: scipy
Requires-Dist: pywin32
Requires-Dist: pypiwin32
Requires-Dist: toolz
Requires-Dist: networkx
Requires-Dist: tqdm
Provides-Extra: dev
Requires-Dist: pythran ; extra == 'dev'
Requires-Dist: numba ; extra == 'dev'
Provides-Extra: doc
Requires-Dist: sphinx ; extra == 'doc'
Requires-Dist: tabulate ; extra == 'doc'
Requires-Dist: sphinx-press-theme ; extra == 'doc'
Provides-Extra: test
Requires-Dist: networkx ; extra == 'test'
Requires-Dist: coverage ; extra == 'test'
Requires-Dist: matplotlib ; extra == 'test'
